{"commit":{"sha":"a18dea908ca2a89cc1c7f4b0416924382ca145e6","date":"2017-12-31T07:29:16+00:00"},"benchmarks":{"coercions":{"Ok":{"runs":[{"stats":{"stats":[null,5062231151.0,24383.0,null,8833507033.0,202632.0,1147.302739,null,1.329243489,1336.03676]},"check":false,"release":false,"state":"Clean"},{"stats":{"stats":[null,5685435744.0,25515.0,null,10176733704.0,224744.0,1325.373293,null,1.465364071,1495.609238]},"check":false,"release":false,"state":"IncrementalStart"},{"stats":{"stats":[null,2147183810.0,21859.0,null,3719394113.0,195452.0,393.562812,null,0.594081847,599.544802]},"check":false,"release":false,"state":"IncrementalClean"},{"stats":{"stats":[null,3120058256.0,23536.0,null,5437322701.0,225440.0,671.807198,null,0.814357964,852.937961]},"check":false,"release":false,"state":{"IncrementalPatched":{"index":0,"name":"println","path":"0-println.patch"}}},{"stats":{"stats":[null,5561629068.0,25142.0,null,10043494192.0,230932.0,1402.472605,null,1.430054589,1468.798662]},"check":false,"release":false,"state":{"IncrementalPatched":{"index":1,"name":"add static arr item","path":"1-add-static-arr-item.patch"}}},{"stats":{"stats":[null,4290630994.0,20152.0,null,7542034307.0,180988.0,1005.355839,null,1.114989809,1124.872938]},"check":false,"release":true,"state":"Clean"},{"stats":{"stats":[null,4948447740.0,22329.0,null,8864597941.0,206084.0,1243.833148,null,1.271181335,1296.574712]},"check":false,"release":true,"state":"IncrementalStart"},{"stats":{"stats":[null,1960489700.0,17734.0,null,3471146777.0,190864.0,467.165433,null,0.534792206,541.047094]},"check":false,"release":true,"state":"IncrementalClean"},{"stats":{"stats":[null,2320924145.0,20105.0,null,4127098969.0,203988.0,511.182041,null,0.6009548,633.444478]},"check":false,"release":true,"state":{"IncrementalPatched":{"index":0,"name":"println","path":"0-println.patch"}}},{"stats":{"stats":[null,4755092335.0,20536.0,null,8720794827.0,211492.0,1153.947044,null,1.212336504,1244.755365]},"check":false,"release":true,"state":{"IncrementalPatched":{"index":1,"name":"add static arr item","path":"1-add-static-arr-item.patch"}}}],"name":"coercions"}},"deep-vector":{"Ok":{"runs":[{"stats":{"stats":[null,8745033368.0,56713.0,null,14546870638.0,266688.0,2163.133151,null,2.283737545,2303.259627]},"check":false,"release":false,"state":"Clean"},{"stats":{"stats":[null,9620926048.0,58670.0,null,16565285326.0,285468.0,2389.036278,null,2.466896368,2532.793464]},"check":false,"release":false,"state":"IncrementalStart"},{"stats":{"stats":[null,3342524912.0,29676.0,null,5783538909.0,250060.0,758.358499,null,0.902177286,909.551342]},"check":false,"release":false,"state":"IncrementalClean"},{"stats":{"stats":[null,9545773858.0,50824.0,null,16556135223.0,287448.0,2374.219533,null,2.427095425,2499.318444]},"check":false,"release":false,"state":{"IncrementalPatched":{"index":0,"name":"println","path":"0-println.patch"}}},{"stats":{"stats":[null,9579381980.0,49484.0,null,16566092059.0,289892.0,2379.109622,null,2.434659993,2509.158951]},"check":false,"release":false,"state":{"IncrementalPatched":{"index":1,"name":"add vec item","path":"1-add-vec-item.patch"}}},{"stats":{"stats":[null,13675644642.0,73739.0,null,20917072938.0,335712.0,3534.081086,null,3.492097653,3555.880013]},"check":false,"release":true,"state":"Clean"},{"stats":{"stats":[null,14415712646.0,75502.0,null,22823630804.0,350424.0,3692.17512,null,3.663274512,3747.395396]},"check":false,"release":true,"state":"IncrementalStart"},{"stats":{"stats":[null,3290963719.0,28433.0,null,5749934679.0,250352.0,881.697723,null,0.890856799,899.695331]},"check":false,"release":true,"state":"IncrementalClean"},{"stats":{"stats":[null,14368098142.0,68162.0,null,22840381568.0,355544.0,3686.797788,null,3.640671991,3733.881571]},"check":false,"release":true,"state":{"IncrementalPatched":{"index":0,"name":"println","path":"0-println.patch"}}},{"stats":{"stats":[null,14315819784.0,66508.0,null,22779046298.0,352252.0,3718.409292,null,3.629810033,3720.512323]},"check":false,"release":true,"state":{"IncrementalPatched":{"index":1,"name":"add vec item","path":"1-add-vec-item.patch"}}}],"name":"deep-vector"}},"encoding":{"Ok":{"runs":[{"stats":{"stats":[null,7805578827.0,7559.0,null,9251243038.0,231408.0,2056.576728,null,1.088854238,2056.578421]},"check":false,"release":false,"state":"Clean"},{"stats":{"stats":[null,10015386139.0,8613.0,null,11763480242.0,260452.0,2654.563447,null,1.411163784,2654.603061]},"check":false,"release":false,"state":"IncrementalStart"},{"stats":{"stats":[null,1981081183.0,4090.0,null,2851341526.0,249216.0,540.852733,null,0.515501868,540.822497]},"check":false,"release":false,"state":"IncrementalClean"},{"stats":{"stats":[null,2020772209.0,3944.0,null,2953931472.0,253696.0,550.840019,null,0.518105774,550.806552]},"check":false,"release":false,"state":{"IncrementalPatched":{"index":0,"name":"println","path":"0-println.patch"}}},{"stats":{"stats":[null,25813223492.0,6252.0,null,22098776932.0,234388.0,6816.795625,null,1.726248176,6816.80597]},"check":false,"release":true,"state":"Clean"},{"stats":{"stats":[null,22646161006.0,7826.0,null,19612226027.0,267344.0,5993.385141,null,1.685730154,5993.395886]},"check":false,"release":true,"state":"IncrementalStart"},{"stats":{"stats":[null,1954359734.0,3803.0,null,2816557658.0,249780.0,525.830717,null,0.504394881,525.819026]},"check":false,"release":true,"state":"IncrementalClean"},{"stats":{"stats":[null,2303331203.0,3723.0,null,3210134581.0,255496.0,617.301955,null,0.545780775,617.273726]},"check":false,"release":true,"state":{"IncrementalPatched":{"index":0,"name":"println","path":"0-println.patch"}}}],"name":"encoding"}},"futures":{"Ok":{"runs":[{"stats":{"stats":[null,4190519970.0,2972.0,null,5661628837.0,168392.0,1083.483956,null,0.911597432,1083.497855]},"check":false,"release":false,"state":"Clean"},{"stats":{"stats":[null,5422213456.0,3772.0,null,7273608939.0,224616.0,1406.952055,null,1.200817307,1406.944547]},"check":false,"release":false,"state":"IncrementalStart"},{"stats":{"stats":[null,2155059896.0,3257.0,null,3225667631.0,216400.0,571.33079,null,0.555632821,571.315018]},"check":false,"release":false,"state":"IncrementalClean"},{"stats":{"stats":[null,2135858049.0,3123.0,null,3204126071.0,215300.0,566.414369,null,0.548401628,566.398607]},"check":false,"release":false,"state":{"IncrementalPatched":{"index":0,"name":"println","path":"0-println.patch"}}},{"stats":{"stats":[null,6539199241.0,3030.0,null,7164947861.0,186044.0,1710.619859,null,0.984375176,1710.618376]},"check":false,"release":true,"state":"Clean"},{"stats":{"stats":[null,6953749485.0,3691.0,null,8073753698.0,231912.0,1813.50328,null,1.208449256,1813.488147]},"check":false,"release":true,"state":"IncrementalStart"},{"stats":{"stats":[null,2148108155.0,3208.0,null,3216151792.0,215888.0,568.217599,null,0.551194394,568.206074]},"check":false,"release":true,"state":"IncrementalClean"},{"stats":{"stats":[null,2122560656.0,3086.0,null,3197517466.0,217184.0,560.930288,null,0.544091083,560.920392]},"check":false,"release":true,"state":{"IncrementalPatched":{"index":0,"name":"println","path":"0-println.patch"}}}],"name":"futures"}},"helloworld":{"Ok":{"runs":[{"stats":{"stats":[null,943816458.0,14599.0,null,1401217455.0,134112.0,142.23743,null,0.273125431,277.226841]},"check":false,"release":false,"state":"Clean"},{"stats":{"stats":[null,1161181341.0,14978.0,null,1675092632.0,154964.0,203.011192,null,0.333390234,337.609605]},"check":false,"release":false,"state":"IncrementalStart"},{"stats":{"stats":[null,971534190.0,14502.0,null,1450676498.0,151412.0,236.936587,null,0.278561974,286.058429]},"check":false,"release":false,"state":"IncrementalClean"},{"stats":{"stats":[null,991961290.0,14600.0,null,1482207308.0,150116.0,238.65318,null,0.28169481,291.628861]},"check":false,"release":false,"state":{"IncrementalPatched":{"index":0,"name":"println","path":"0-println.patch"}}},{"stats":{"stats":[null,975311329.0,14587.0,null,1438209093.0,132400.0,235.480046,null,0.278857973,286.212928]},"check":false,"release":true,"state":"Clean"},{"stats":{"stats":[null,1181171007.0,14939.0,null,1689578005.0,152996.0,203.365335,null,0.328991464,337.410368]},"check":false,"release":true,"state":"IncrementalStart"},{"stats":{"stats":[null,975633919.0,14601.0,null,1456427382.0,154040.0,213.566513,null,0.280317708,287.250422]},"check":false,"release":true,"state":"IncrementalClean"},{"stats":{"stats":[null,1007727156.0,14568.0,null,1498544642.0,153120.0,244.88839,null,0.281848545,296.250124]},"check":false,"release":true,"state":{"IncrementalPatched":{"index":0,"name":"println","path":"0-println.patch"}}}],"name":"helloworld"}},"html5ever":{"Ok":{"runs":[{"stats":{"stats":[null,12624784264.0,11540.0,null,17927902898.0,296840.0,3274.392585,null,2.460241245,3274.372486]},"check":false,"release":false,"state":"Clean"},{"stats":{"stats":[null,15711263660.0,13639.0,null,24494905899.0,365924.0,4058.811374,null,3.261021343,4058.816631]},"check":false,"release":false,"state":"IncrementalStart"},{"stats":{"stats":[null,4649258098.0,8852.0,null,7582958680.0,337564.0,1228.015886,null,1.212027683,1227.982524]},"check":false,"release":false,"state":"IncrementalClean"},{"stats":{"stats":[null,32616320471.0,32575.0,null,32943512553.0,281488.0,8617.401014,null,3.348404907,8617.3895]},"check":false,"release":true,"state":"Clean"},{"stats":{"stats":[null,27657727887.0,13803.0,null,31866676715.0,386308.0,7218.492383,null,3.594733339,7218.493349]},"check":false,"release":true,"state":"IncrementalStart"},{"stats":{"stats":[null,4632972594.0,8633.0,null,7552224499.0,335852.0,1219.421543,null,1.192674704,1219.402947]},"check":false,"release":true,"state":"IncrementalClean"}],"name":"html5ever"}},"hyper":{"Ok":{"runs":[{"stats":{"stats":[null,17803137861.0,27254.0,null,20225437214.0,271964.0,4663.082697,null,2.513429028,4663.082972]},"check":false,"release":false,"state":"Clean"},{"stats":{"stats":[null,22880604332.0,19890.0,null,26367825285.0,357460.0,6006.40915,null,3.326952519,6006.518556]},"check":false,"release":false,"state":"IncrementalStart"},{"stats":{"stats":[null,4220085690.0,6125.0,null,5605863145.0,342792.0,1129.805959,null,1.071501426,1129.693179]},"check":false,"release":false,"state":"IncrementalClean"},{"stats":{"stats":[null,5154548673.0,5942.0,null,6669489761.0,352240.0,1376.735026,null,1.184183268,1376.663799]},"check":false,"release":false,"state":{"IncrementalPatched":{"index":0,"name":"println","path":"0-println.patch"}}},{"stats":{"stats":[null,70949202857.0,12369.0,null,56470783426.0,294012.0,18695.465046,null,4.512568017,18695.473977]},"check":false,"release":true,"state":"Clean"},{"stats":{"stats":[null,61468873889.0,10426.0,null,48723614531.0,360884.0,16234.267445,null,4.036576654,16234.279799]},"check":false,"release":true,"state":"IncrementalStart"},{"stats":{"stats":[null,4131949251.0,5585.0,null,5513575885.0,336500.0,1099.381933,null,1.049142071,1099.325254]},"check":false,"release":true,"state":"IncrementalClean"},{"stats":{"stats":[null,11177066863.0,5458.0,null,12731409833.0,357808.0,2912.051121,null,2.10357426,2912.012062]},"check":false,"release":true,"state":{"IncrementalPatched":{"index":0,"name":"println","path":"0-println.patch"}}}],"name":"hyper"}},"inflate":{"Ok":{"runs":[{"stats":{"stats":[null,12533416510.0,24967.0,null,23077967715.0,271792.0,3216.596853,null,3.034282659,3216.588959]},"check":false,"release":false,"state":"Clean"},{"stats":{"stats":[null,14025004994.0,20287.0,null,25414045540.0,291228.0,3599.646309,null,3.332411909,3599.668959]},"check":false,"release":false,"state":"IncrementalStart"},{"stats":{"stats":[null,1732432890.0,4557.0,null,2628168510.0,304344.0,472.113579,null,0.459436382,472.090441]},"check":false,"release":false,"state":"IncrementalClean"},{"stats":{"stats":[null,13806629772.0,23409.0,null,25125864745.0,309496.0,3549.596459,null,3.270588514,3549.605671]},"check":false,"release":false,"state":{"IncrementalPatched":{"index":0,"name":"println","path":"0-println.patch"}}},{"stats":{"stats":[null,46810274264.0,66774.0,null,79859495867.0,272008.0,11854.963054,null,11.612608799,11854.947325]},"check":false,"release":true,"state":"Clean"},{"stats":{"stats":[null,37144080754.0,39427.0,null,66538995349.0,301252.0,9410.292908,null,9.160043216,9410.29186]},"check":false,"release":true,"state":"IncrementalStart"},{"stats":{"stats":[null,1694264767.0,4513.0,null,2595376796.0,301148.0,459.569009,null,0.450696462,459.560706]},"check":false,"release":true,"state":"IncrementalClean"},{"stats":{"stats":[null,36679539273.0,43118.0,null,66373281380.0,315136.0,9297.369186,null,9.053638119,9297.368896]},"check":false,"release":true,"state":{"IncrementalPatched":{"index":0,"name":"println","path":"0-println.patch"}}}],"name":"inflate"}},"parser":{"Ok":{"runs":[{"stats":{"stats":[null,1080679230.0,14957.0,null,1588041043.0,140344.0,230.552689,null,0.311409305,311.606406]},"check":false,"release":false,"state":"Clean"},{"stats":{"stats":[null,1365257329.0,15015.0,null,1980682728.0,166888.0,257.678463,null,0.381694341,385.538914]},"check":false,"release":false,"state":"IncrementalStart"},{"stats":{"stats":[null,1065281479.0,15087.0,null,1598431275.0,169616.0,219.565301,null,0.305053761,311.49875]},"check":false,"release":false,"state":"IncrementalClean"},{"stats":{"stats":[null,1033664778.0,15512.0,null,1582305473.0,162572.0,169.229357,null,0.295862829,303.091366]},"check":false,"release":false,"state":{"IncrementalPatched":{"index":0,"name":"println","path":"0-println.patch"}}},{"stats":{"stats":[null,1117943085.0,14838.0,null,1625893522.0,139796.0,185.676228,null,0.315829282,322.666644]},"check":false,"release":true,"state":"Clean"},{"stats":{"stats":[null,1419210113.0,14838.0,null,1995769457.0,165548.0,329.09051,null,0.389231145,399.075726]},"check":false,"release":true,"state":"IncrementalStart"},{"stats":{"stats":[null,1084750174.0,15290.0,null,1604452982.0,166800.0,181.343781,null,0.308256251,316.575157]},"check":false,"release":true,"state":"IncrementalClean"},{"stats":{"stats":[null,1071849421.0,15478.0,null,1588373961.0,167440.0,259.986702,null,0.304700218,313.421669]},"check":false,"release":true,"state":{"IncrementalPatched":{"index":0,"name":"println","path":"0-println.patch"}}}],"name":"parser"}},"piston-image":{"Ok":{"runs":[{"stats":{"stats":[null,40069198098.0,57415.0,null,45253347980.0,364848.0,10500.851611,null,5.094259038,10500.870117]},"check":false,"release":false,"state":"Clean"},{"stats":{"stats":[null,47723507210.0,48192.0,null,55026581212.0,417376.0,12490.76438,null,6.289203955,12490.806402]},"check":false,"release":false,"state":"IncrementalStart"},{"stats":{"stats":[null,6019280123.0,7039.0,null,8363881001.0,417488.0,1603.769932,null,1.530045131,1603.66568]},"check":false,"release":false,"state":"IncrementalClean"},{"stats":{"stats":[null,178344229301.0,43966.0,null,150759161061.0,380212.0,47029.876109,null,10.707772991,47029.891466]},"check":false,"release":true,"state":"Clean"},{"stats":{"stats":[null,136136128520.0,32425.0,null,109903307783.0,413776.0,35942.041425,null,8.157619548,35942.082133]},"check":false,"release":true,"state":"IncrementalStart"},{"stats":{"stats":[null,5887689024.0,6413.0,null,8166683390.0,392756.0,1545.672659,null,1.483967356,1545.61043]},"check":false,"release":true,"state":"IncrementalClean"}],"name":"piston-image"}},"regex":{"Ok":{"runs":[{"stats":{"stats":[null,26220916696.0,40356.0,null,26512226594.0,309404.0,6925.868653,null,2.864112535,6925.874766]},"check":false,"release":false,"state":"Clean"},{"stats":{"stats":[null,33147627128.0,40168.0,null,32045023053.0,360396.0,8791.428516,null,3.210140195,8791.431611]},"check":false,"release":false,"state":"IncrementalStart"},{"stats":{"stats":[null,3404525291.0,4876.0,null,4861466255.0,315988.0,915.566796,null,0.871452766,915.522778]},"check":false,"release":false,"state":"IncrementalClean"},{"stats":{"stats":[null,9217027526.0,9271.0,null,10941605303.0,346008.0,2433.186322,null,1.454502689,2433.142712]},"check":false,"release":false,"state":{"IncrementalPatched":{"index":0,"name":"compile one","path":"0-compile-one.patch"}}},{"stats":{"stats":[null,4054901608.0,5289.0,null,5516561310.0,327424.0,1083.892354,null,0.934257232,1083.851445]},"check":false,"release":false,"state":{"IncrementalPatched":{"index":1,"name":"is valid cap letter","path":"1-is-valid-cap-letter.patch"}}},{"stats":{"stats":[null,6417885892.0,9106.0,null,8253701876.0,341548.0,1704.885183,null,1.251448378,1704.839897]},"check":false,"release":false,"state":{"IncrementalPatched":{"index":2,"name":"expand","path":"2-expand.patch"}}},{"stats":{"stats":[null,11369144631.0,15337.0,null,13670588863.0,358620.0,3004.365788,null,1.837351023,3004.336807]},"check":false,"release":false,"state":{"IncrementalPatched":{"index":3,"name":"Compiler new","path":"3-Compiler-new.patch"}}},{"stats":{"stats":[null,11534071404.0,15396.0,null,13679707290.0,358916.0,3043.83333,null,1.850608929,3043.795116]},"check":false,"release":false,"state":{"IncrementalPatched":{"index":4,"name":"reverse","path":"4-reverse.patch"}}},{"stats":{"stats":[null,3602068727.0,4903.0,null,5103904586.0,322712.0,964.306112,null,0.88939736,964.261054]},"check":false,"release":false,"state":{"IncrementalPatched":{"index":5,"name":"byte frequencies","path":"5-byte-frequencies.patch"}}},{"stats":{"stats":[null,22985948107.0,34841.0,null,22506478637.0,386932.0,6131.509884,null,2.147118236,6131.521822]},"check":false,"release":false,"state":{"IncrementalPatched":{"index":6,"name":"sparse set","path":"6-sparse-set.patch"}}},{"stats":{"stats":[null,22926074405.0,34685.0,null,21984155025.0,391156.0,6115.993137,null,2.090013879,6115.986719]},"check":false,"release":false,"state":{"IncrementalPatched":{"index":7,"name":"Job","path":"7-Job.patch"}}},{"stats":{"stats":[null,105235937503.0,37217.0,null,87954621915.0,277872.0,27760.583157,null,6.309006943,27760.612873]},"check":false,"release":true,"state":"Clean"},{"stats":{"stats":[null,81591045780.0,22512.0,null,67084533574.0,356308.0,21551.882247,null,4.82783002,21551.905429]},"check":false,"release":true,"state":"IncrementalStart"},{"stats":{"stats":[null,3368685833.0,4505.0,null,4770619786.0,313572.0,892.640423,null,0.853550725,892.633154]},"check":false,"release":true,"state":"IncrementalClean"},{"stats":{"stats":[null,11411694498.0,4933.0,null,13404904393.0,337848.0,2967.711881,null,1.774655363,2967.691253]},"check":false,"release":true,"state":{"IncrementalPatched":{"index":0,"name":"compile one","path":"0-compile-one.patch"}}},{"stats":{"stats":[null,3512700259.0,5021.0,null,4996797076.0,315780.0,932.188292,null,0.859722331,932.15227]},"check":false,"release":true,"state":{"IncrementalPatched":{"index":1,"name":"is valid cap letter","path":"1-is-valid-cap-letter.patch"}}},{"stats":{"stats":[null,7744574770.0,6860.0,null,10591431620.0,319972.0,2002.480645,null,1.8223246,2002.451952]},"check":false,"release":true,"state":{"IncrementalPatched":{"index":2,"name":"expand","path":"2-expand.patch"}}},{"stats":{"stats":[null,18301409984.0,9074.0,null,21981029869.0,343448.0,4754.587902,null,2.700877283,4754.573009]},"check":false,"release":true,"state":{"IncrementalPatched":{"index":3,"name":"Compiler new","path":"3-Compiler-new.patch"}}},{"stats":{"stats":[null,18350165953.0,9385.0,null,21988725652.0,342840.0,4771.758944,null,2.652905938,4771.753188]},"check":false,"release":true,"state":{"IncrementalPatched":{"index":4,"name":"reverse","path":"4-reverse.patch"}}},{"stats":{"stats":[null,4185028109.0,4582.0,null,5666319745.0,314112.0,1105.706013,null,0.977701902,1105.677532]},"check":false,"release":true,"state":{"IncrementalPatched":{"index":5,"name":"byte frequencies","path":"5-byte-frequencies.patch"}}},{"stats":{"stats":[null,48597421770.0,18007.0,null,45432929761.0,371316.0,12851.041843,null,3.178355101,12851.038179]},"check":false,"release":true,"state":{"IncrementalPatched":{"index":6,"name":"sparse set","path":"6-sparse-set.patch"}}},{"stats":{"stats":[null,48831563308.0,17539.0,null,45076548289.0,368656.0,12916.446417,null,3.124429292,12916.45944]},"check":false,"release":true,"state":{"IncrementalPatched":{"index":7,"name":"Job","path":"7-Job.patch"}}}],"name":"regex"}},"regression-31157":{"Ok":{"runs":[{"stats":{"stats":[null,9363174234.0,11293.0,null,10710692601.0,199780.0,2452.803164,null,1.267356535,2452.822835]},"check":false,"release":false,"state":"Clean"},{"stats":{"stats":[null,12392782809.0,12178.0,null,16526973723.0,236752.0,3237.668681,null,1.890036562,3237.652655]},"check":false,"release":false,"state":"IncrementalStart"},{"stats":{"stats":[null,1952302245.0,3332.0,null,3158380182.0,219548.0,526.013962,null,0.504868667,525.991361]},"check":false,"release":false,"state":"IncrementalClean"},{"stats":{"stats":[null,2249667546.0,3297.0,null,3750889281.0,236080.0,607.216844,null,0.548639867,607.202378]},"check":false,"release":false,"state":{"IncrementalPatched":{"index":0,"name":"println","path":"0-println.patch"}}},{"stats":{"stats":[null,32953219700.0,7698.0,null,30856072440.0,199924.0,8575.239628,null,3.700399547,8575.247156]},"check":false,"release":true,"state":"Clean"},{"stats":{"stats":[null,26602002767.0,5675.0,null,27387913478.0,253724.0,6927.195002,null,3.253065181,6927.194315]},"check":false,"release":true,"state":"IncrementalStart"},{"stats":{"stats":[null,1875050951.0,3198.0,null,3100690041.0,218680.0,499.538436,null,0.482009111,499.525994]},"check":false,"release":true,"state":"IncrementalClean"},{"stats":{"stats":[null,3086187577.0,3107.0,null,4890627039.0,223412.0,811.901687,null,0.658184001,811.888783]},"check":false,"release":true,"state":{"IncrementalPatched":{"index":0,"name":"println","path":"0-println.patch"}}}],"name":"regression-31157"}},"script-servo":{"Ok":{"runs":[{"stats":{"stats":[null,3810121683219.0,946021.0,null,2795500042396.0,4568428.0,1005164.194595,null,214.377190527,1005164.515919]},"check":false,"release":true,"state":"Clean"},{"stats":{"stats":[null,2835633682650.0,666042.0,null,2202828636068.0,6343992.0,746578.893125,null,191.650591316,746579.78686]},"check":false,"release":true,"state":"IncrementalStart"},{"stats":{"stats":[null,133494002919.0,126324.0,null,179553083583.0,5792764.0,34617.032482,null,33.570184288,34616.542255]},"check":false,"release":true,"state":"IncrementalClean"},{"stats":{"stats":[null,174287411753.0,119930.0,null,219110356056.0,5519104.0,45330.068939,null,35.27333142,45329.907093]},"check":false,"release":true,"state":{"IncrementalPatched":{"index":0,"name":"debugging println in dependency","path":"0-debugging-println-in-dependency.patch"}}},{"stats":{"stats":[null,384383693659.0,140745.0,null,458845854885.0,5870376.0,98324.526349,null,92.10961552,98324.16376]},"check":false,"release":true,"state":{"IncrementalPatched":{"index":1,"name":"debugging println","path":"1-debugging-println.patch"}}},{"stats":{"stats":[null,2709451454128.0,661348.0,null,2071654214233.0,6990204.0,713932.415663,null,176.698506646,713932.678442]},"check":false,"release":true,"state":{"IncrementalPatched":{"index":2,"name":"commit 8b0f58c8a","path":"2-commit-8b0f58c8a.patch"}}}],"name":"script-servo"}},"style-servo":{"Ok":{"runs":[{"stats":{"stats":[null,1221834960378.0,373890.0,null,1013645441823.0,1984340.0,322105.642627,null,76.149712837,322105.817067]},"check":false,"release":true,"state":"Clean"},{"stats":{"stats":[null,1206954004176.0,327997.0,null,1141377571300.0,2717756.0,317380.88588,null,92.921336742,317380.962688]},"check":false,"release":true,"state":"IncrementalStart"},{"stats":{"stats":[null,266248657522.0,131600.0,null,283119835617.0,2976164.0,69833.867012,null,29.205009245,69833.656168]},"check":false,"release":true,"state":"IncrementalClean"},{"stats":{"stats":[null,880744931004.0,274905.0,null,810755265025.0,2984348.0,232125.358834,null,62.878560908,232125.326497]},"check":false,"release":true,"state":{"IncrementalPatched":{"index":0,"name":"debugging println","path":"0-debugging-println.patch"}}},{"stats":{"stats":[null,976508111515.0,302537.0,null,834836937346.0,3145904.0,257873.793184,null,64.398015465,257874.054878]},"check":false,"release":true,"state":{"IncrementalPatched":{"index":1,"name":"b9b3e592dd cherry picked","path":"1-b9b3e592dd-cherry-picked.patch"}}}],"name":"style-servo"}},"syn":{"Ok":{"runs":[{"stats":{"stats":[null,13619651303.0,14531.0,null,15446835584.0,263864.0,3575.849467,null,1.827082285,3575.86896]},"check":false,"release":false,"state":"Clean"},{"stats":{"stats":[null,17055603863.0,15271.0,null,20955189431.0,336892.0,4492.565034,null,2.480592327,4492.565161]},"check":false,"release":false,"state":"IncrementalStart"},{"stats":{"stats":[null,3084367275.0,5025.0,null,4213359084.0,323884.0,827.042942,null,0.78977607,826.997919]},"check":false,"release":false,"state":"IncrementalClean"},{"stats":{"stats":[null,6442278443.0,6807.0,null,8269146078.0,347468.0,1710.219714,null,1.145002076,1710.183961]},"check":false,"release":false,"state":{"IncrementalPatched":{"index":0,"name":"println","path":"0-println.patch"}}},{"stats":{"stats":[null,71559686722.0,15109.0,null,57307479620.0,287136.0,18881.577811,null,3.992383858,18881.604798]},"check":false,"release":true,"state":"Clean"},{"stats":{"stats":[null,48607723654.0,9151.0,null,41931709964.0,364916.0,12817.650993,null,3.383755776,12817.655505]},"check":false,"release":true,"state":"IncrementalStart"},{"stats":{"stats":[null,3009565011.0,4717.0,null,4158138275.0,322088.0,802.769964,null,0.770133869,802.74883]},"check":false,"release":true,"state":"IncrementalClean"},{"stats":{"stats":[null,14977324519.0,4877.0,null,15537779789.0,358204.0,3958.725984,null,1.481607734,3958.716379]},"check":false,"release":true,"state":{"IncrementalPatched":{"index":0,"name":"println","path":"0-println.patch"}}}],"name":"syn"}},"tokio-webpush-simple":{"Ok":{"runs":[{"stats":{"stats":[null,22157142236.0,61539.0,null,25257632272.0,301680.0,5824.254892,null,3.38480852,5906.669324]},"check":false,"release":false,"state":"Clean"},{"stats":{"stats":[null,28385432802.0,65813.0,null,34234887517.0,377568.0,7487.08171,null,4.361993047,7521.654169]},"check":false,"release":false,"state":"IncrementalStart"},{"stats":{"stats":[null,7080625996.0,47846.0,null,9350179598.0,367328.0,1913.639091,null,1.905408535,1967.526902]},"check":false,"release":false,"state":"IncrementalClean"},{"stats":{"stats":[null,26849406642.0,69589.0,null,32142628818.0,399096.0,7135.479127,null,3.988750024,7150.215029]},"check":false,"release":false,"state":{"IncrementalPatched":{"index":0,"name":"minor change","path":"0-minor-change.patch"}}},{"stats":{"stats":[null,113550695908.0,40999.0,null,94411885459.0,324692.0,29916.484364,null,7.318289045,29946.513323]},"check":false,"release":true,"state":"Clean"},{"stats":{"stats":[null,91611924905.0,39033.0,null,70971049359.0,372004.0,24254.101104,null,4.947447133,24283.625305]},"check":false,"release":true,"state":"IncrementalStart"},{"stats":{"stats":[null,4770619889.0,27350.0,null,6729795353.0,351524.0,1284.601698,null,1.265595239,1320.555216]},"check":false,"release":true,"state":"IncrementalClean"},{"stats":{"stats":[null,90873006182.0,37915.0,null,69095435533.0,386616.0,24102.458376,null,4.586179841,24115.432791]},"check":false,"release":true,"state":{"IncrementalPatched":{"index":0,"name":"minor change","path":"0-minor-change.patch"}}}],"name":"tokio-webpush-simple"}},"tuple-stress":{"Ok":{"runs":[{"stats":{"stats":[null,18483461961.0,29537.0,null,27045212317.0,394616.0,4703.419438,null,4.680534004,4729.192393]},"check":false,"release":false,"state":"Clean"},{"stats":{"stats":[null,21876339248.0,30928.0,null,34355583248.0,599456.0,5529.820584,null,5.440594396,5645.68967]},"check":false,"release":false,"state":"IncrementalStart"},{"stats":{"stats":[null,6609425917.0,28811.0,null,10812015298.0,381980.0,1692.70724,null,1.734893194,1741.354233]},"check":false,"release":false,"state":"IncrementalClean"},{"stats":{"stats":[null,21723447151.0,33961.0,null,34151088929.0,620524.0,5513.462548,null,5.41680872,5637.772005]},"check":false,"release":false,"state":{"IncrementalPatched":{"index":0,"name":"new row","path":"0-new-row.patch"}}},{"stats":{"stats":[null,16879208129.0,29146.0,null,24923628879.0,393932.0,4226.963382,null,4.309999503,4356.339967]},"check":false,"release":true,"state":"Clean"},{"stats":{"stats":[null,20212130175.0,32066.0,null,32156956993.0,424904.0,5079.931684,null,5.156470302,5225.477025]},"check":false,"release":true,"state":"IncrementalStart"},{"stats":{"stats":[null,6582468202.0,27666.0,null,10761813885.0,378604.0,1595.941853,null,1.733726108,1741.301218]},"check":false,"release":true,"state":"IncrementalClean"},{"stats":{"stats":[null,20204810359.0,34290.0,null,31999879396.0,447616.0,5106.86898,null,5.087365561,5162.054861]},"check":false,"release":true,"state":{"IncrementalPatched":{"index":0,"name":"new row","path":"0-new-row.patch"}}}],"name":"tuple-stress"}},"unify-linearly":{"Ok":{"runs":[{"stats":{"stats":[null,1256140959.0,14496.0,null,1931147566.0,140708.0,222.189926,null,0.346271963,357.244617]},"check":false,"release":false,"state":"Clean"},{"stats":{"stats":[null,1533582743.0,14996.0,null,2292449237.0,159436.0,375.214969,null,0.411749064,429.090391]},"check":false,"release":false,"state":"IncrementalStart"},{"stats":{"stats":[null,1019817130.0,15093.0,null,1561567155.0,162512.0,168.187874,null,0.29501787,300.778949]},"check":false,"release":false,"state":"IncrementalClean"},{"stats":{"stats":[null,1251742466.0,15248.0,null,1890484836.0,161260.0,313.534134,null,0.335091187,361.287147]},"check":false,"release":false,"state":{"IncrementalPatched":{"index":0,"name":"dummy fn","path":"0-dummy-fn.patch"}}},{"stats":{"stats":[null,1268013359.0,13703.0,null,1945966651.0,130292.0,222.454995,null,0.351778717,357.821413]},"check":false,"release":true,"state":"Clean"},{"stats":{"stats":[null,1522040582.0,13920.0,null,2296388260.0,161780.0,387.649985,null,0.408693522,426.621434]},"check":false,"release":true,"state":"IncrementalStart"},{"stats":{"stats":[null,1036562634.0,13983.0,null,1564070110.0,155048.0,251.787942,null,0.296016131,305.34347]},"check":false,"release":true,"state":"IncrementalClean"},{"stats":{"stats":[null,1226320461.0,15225.0,null,1892858237.0,159504.0,249.214402,null,0.337907157,353.516523]},"check":false,"release":true,"state":{"IncrementalPatched":{"index":0,"name":"dummy fn","path":"0-dummy-fn.patch"}}}],"name":"unify-linearly"}},"unused-warnings":{"Ok":{"runs":[{"stats":{"stats":[null,2002301819.0,22961.0,null,2974329938.0,159604.0,429.877766,null,0.573873536,564.795051]},"check":false,"release":false,"state":"Clean"},{"stats":{"stats":[null,3082280394.0,29213.0,null,4349595896.0,252540.0,786.056443,null,0.837262003,840.346532]},"check":false,"release":false,"state":"IncrementalStart"},{"stats":{"stats":[null,3058690330.0,29440.0,null,4257309954.0,273176.0,788.1438,null,0.797665442,839.18481]},"check":false,"release":false,"state":"IncrementalClean"},{"stats":{"stats":[null,3024745678.0,27771.0,null,4220962052.0,269432.0,695.102229,null,0.79277566,831.128594]},"check":false,"release":false,"state":{"IncrementalPatched":{"index":0,"name":"dummy fn","path":"0-dummy-fn.patch"}}},{"stats":{"stats":[null,2067983103.0,22881.0,null,3016089226.0,159436.0,436.309013,null,0.560258406,572.063688]},"check":false,"release":true,"state":"Clean"},{"stats":{"stats":[null,3089734682.0,28949.0,null,4368902900.0,252736.0,706.903544,null,0.835719324,843.110774]},"check":false,"release":true,"state":"IncrementalStart"},{"stats":{"stats":[null,3149033289.0,27644.0,null,4267056559.0,269844.0,757.256922,null,0.82651303,864.010848]},"check":false,"release":true,"state":"IncrementalClean"},{"stats":{"stats":[null,3095956155.0,27653.0,null,4242877422.0,270652.0,798.575641,null,0.789350349,849.35628]},"check":false,"release":true,"state":{"IncrementalPatched":{"index":0,"name":"dummy fn","path":"0-dummy-fn.patch"}}}],"name":"unused-warnings"}}},"triple":"x86_64-unknown-linux-gnu"}