{
    "header": {
        "date": "Thu Mar 17 11:08:44 2016 -0700", 
        "commit": "b12b4e4e3266644d519647afc2943cefa2026e07"
    }, 
    "times": [
        {
            "loc": 956, 
            "post_nc": 54798, 
            "crate": "inflate-0.1.0", 
            "pre_nc": 4761, 
            "times": {
                "drop-impl checking": {
                    "percent": 0.0, 
                    "time": 0.0
                }, 
                "stability checking": {
                    "percent": 0.048177292436165094, 
                    "time": 0.0022500000000000003
                }, 
                "intrinsic checking": {
                    "percent": 0.0, 
                    "time": 0.0
                }, 
                "complete gated feature checking 1": {
                    "percent": 0.02141212997162893, 
                    "time": 0.001
                }, 
                "looking for plugin registrar": {
                    "percent": 0.0, 
                    "time": 0.0
                }, 
                "complete gated feature checking 2": {
                    "percent": 0.0, 
                    "time": 0.0
                }, 
                "type collecting": {
                    "percent": 0.02141212997162893, 
                    "time": 0.001
                }, 
                "const fn bodies and arguments": {
                    "percent": 0.0, 
                    "time": 0.0
                }, 
                "privacy checking": {
                    "percent": 0.04282425994325786, 
                    "time": 0.002
                }, 
                "configuration 1": {
                    "percent": 0.02141212997162893, 
                    "time": 0.001
                }, 
                "item-bodies checking": {
                    "percent": 62.07376478775226, 
                    "time": 2.899
                }, 
                "looking for entry point": {
                    "percent": 0.0, 
                    "time": 0.0
                }, 
                "effect checking": {
                    "percent": 0.02141212997162893, 
                    "time": 0.001
                }, 
                "linking": {
                    "percent": 0.7280124190353836, 
                    "time": 0.034
                }, 
                "gated macro checking": {
                    "percent": 0.0, 
                    "time": 0.0
                }, 
                "MIR passes": {
                    "percent": 0.29976981960280497, 
                    "time": 0.014
                }, 
                "liveness checking": {
                    "percent": 6.744820941063113, 
                    "time": 0.315
                }, 
                "assigning node ids": {
                    "percent": 0.08564851988651571, 
                    "time": 0.004
                }, 
                "language item collection": {
                    "percent": 0.02141212997162893, 
                    "time": 0.001
                }, 
                "resolving dependency formats": {
                    "percent": 0.0, 
                    "time": 0.0
                }, 
                "checking for inline asm in case the target doesn't support it": {
                    "percent": 0.0, 
                    "time": 0.0
                }, 
                "lifetime resolution": {
                    "percent": 0.02141212997162893, 
                    "time": 0.001
                }, 
                "translation": {
                    "percent": 8.125903324233178, 
                    "time": 0.3795
                }, 
                "stability index": {
                    "percent": 0.0, 
                    "time": 0.0
                }, 
                "variance inference": {
                    "percent": 0.0, 
                    "time": 0.0
                }, 
                "unused lib feature checking": {
                    "percent": 0.0, 
                    "time": 0.0
                }, 
                "borrow checking": {
                    "percent": 4.459076066591724, 
                    "time": 0.20825
                }, 
                "maybe building test harness": {
                    "percent": 0.08564851988651571, 
                    "time": 0.004
                }, 
                "prelude injection": {
                    "percent": 0.08564851988651571, 
                    "time": 0.004
                }, 
                "recursion limit": {
                    "percent": 0.0, 
                    "time": 0.0
                }, 
                "loop checking": {
                    "percent": 0.0, 
                    "time": 0.0
                }, 
                "item-types checking": {
                    "percent": 0.04282425994325786, 
                    "time": 0.002
                }, 
                "gated configuration checking": {
                    "percent": 0.0, 
                    "time": 0.0
                }, 
                "crate injection": {
                    "percent": 0.0, 
                    "time": 0.0
                }, 
                "match checking": {
                    "percent": 0.06423638991488678, 
                    "time": 0.003
                }, 
                "expansion": {
                    "percent": 1.8842674375033457, 
                    "time": 0.088
                }, 
                "LLVM passes": {
                    "percent": 11.9907927841122, 
                    "time": 0.56
                }, 
                "MIR dump": {
                    "percent": 0.5834805417268882, 
                    "time": 0.02725
                }, 
                "region resolution": {
                    "percent": 0.10706064985814463, 
                    "time": 0.005
                }, 
                "lint checking": {
                    "percent": 0.369359242010599, 
                    "time": 0.01725
                }, 
                "early lint checks": {
                    "percent": 0.08564851988651571, 
                    "time": 0.004
                }, 
                "configuration 2": {
                    "percent": 0.19270916974466032, 
                    "time": 0.009
                }, 
                "lowering ast -> hir": {
                    "percent": 0.2890637546169905, 
                    "time": 0.0135
                }, 
                "checking that all macro invocations are gone": {
                    "percent": 0.0, 
                    "time": 0.0
                }, 
                "parsing": {
                    "percent": 0.15523794229430973, 
                    "time": 0.00725
                }, 
                "rvalue checking": {
                    "percent": 0.19270916974466032, 
                    "time": 0.009
                }, 
                "death checking": {
                    "percent": 0.06423638991488678, 
                    "time": 0.003
                }, 
                "const checking": {
                    "percent": 0.29976981960280497, 
                    "time": 0.014
                }, 
                "plugin loading": {
                    "percent": 0.0, 
                    "time": 0.0
                }, 
                "wf checking": {
                    "percent": 0.04282425994325786, 
                    "time": 0.002
                }, 
                "static item recursion checking": {
                    "percent": 0.0, 
                    "time": 0.0
                }, 
                "attribute checking": {
                    "percent": 0.0, 
                    "time": 0.0
                }, 
                "macro loading": {
                    "percent": 0.06423638991488678, 
                    "time": 0.003
                }, 
                "plugin registration": {
                    "percent": 0.0, 
                    "time": 0.0
                }, 
                "coherence checking": {
                    "percent": 0.32118194957443386, 
                    "time": 0.015
                }, 
                "indexing hir": {
                    "percent": 0.08564851988651571, 
                    "time": 0.004
                }, 
                "resolution": {
                    "percent": 0.2355334296879182, 
                    "time": 0.011
                }, 
                "reachability checking": {
                    "percent": 0.0, 
                    "time": 0.0
                }, 
                "external crate/lib resolution": {
                    "percent": 0.02141212997162893, 
                    "time": 0.001
                }
            }, 
            "total": 4.67025, 
            "rss": {
                "drop-impl checking": 91, 
                "stability checking": 103, 
                "intrinsic checking": 92, 
                "complete gated feature checking 1": 43, 
                "looking for plugin registrar": 54, 
                "complete gated feature checking 2": 43, 
                "type collecting": 57, 
                "const fn bodies and arguments": 43, 
                "privacy checking": 92, 
                "configuration 1": 32, 
                "item-bodies checking": 91, 
                "looking for entry point": 54, 
                "effect checking": 92, 
                "linking": 88, 
                "gated macro checking": 32, 
                "MIR passes": 103, 
                "liveness checking": 92, 
                "assigning node ids": 43, 
                "language item collection": 45, 
                "resolving dependency formats": 103, 
                "checking for inline asm in case the target doesn't support it": 43, 
                "lifetime resolution": 54, 
                "translation": 125, 
                "stability index": 92, 
                "variance inference": 57, 
                "unused lib feature checking": 103, 
                "borrow checking": 103, 
                "maybe building test harness": 43, 
                "prelude injection": 43, 
                "recursion limit": 32, 
                "loop checking": 54, 
                "item-types checking": 71, 
                "gated configuration checking": 43, 
                "crate injection": 32, 
                "match checking": 92, 
                "expansion": 43, 
                "LLVM passes": 87, 
                "MIR dump": 103, 
                "region resolution": 54, 
                "lint checking": 103, 
                "early lint checks": 48, 
                "configuration 2": 43, 
                "lowering ast -> hir": 47, 
                "checking that all macro invocations are gone": 43, 
                "parsing": 31, 
                "rvalue checking": 92, 
                "death checking": 103, 
                "const checking": 92, 
                "plugin loading": 35, 
                "wf checking": 71, 
                "static item recursion checking": 54, 
                "attribute checking": 48, 
                "macro loading": 35, 
                "plugin registration": 35, 
                "coherence checking": 71, 
                "indexing hir": 48, 
                "resolution": 54, 
                "reachability checking": 103, 
                "external crate/lib resolution": 45
            }
        }
    ]
}