{
    "header": {
        "date": "Fri Jun 17 11:12:00 2016 -0700", 
        "commit": "1f9423a87aadacf1dc8f52e3df56f61a7415d4d7"
    }, 
    "times": [
        {
            "loc": 639, 
            "post_nc": 69643, 
            "crate": "regex-macros.0.1.30", 
            "pre_nc": 2072, 
            "times": {
                "looking for plugin registrar": {
                    "percent": 0.0, 
                    "time": 0.0
                }, 
                "looking for entry point": {
                    "percent": 0.0, 
                    "time": 0.0
                }, 
                "type collecting": {
                    "percent": 1.2738853503184715, 
                    "time": 0.014
                }, 
                "parsing": {
                    "percent": 0.18198362147406735, 
                    "time": 0.002
                }, 
                "item-bodies checking": {
                    "percent": 79.41310282074613, 
                    "time": 0.8727499999999999
                }, 
                "configuration": {
                    "percent": 0.0, 
                    "time": 0.0
                }, 
                "assigning node ids": {
                    "percent": 0.3639672429481347, 
                    "time": 0.004
                }, 
                "language item collection": {
                    "percent": 0.04549590536851684, 
                    "time": 0.0005
                }, 
                "complete gated feature checking": {
                    "percent": 0.09099181073703368, 
                    "time": 0.001
                }, 
                "checking for inline asm in case the target doesn't support it": {
                    "percent": 0.0, 
                    "time": 0.0
                }, 
                "lifetime resolution": {
                    "percent": 0.06824385805277526, 
                    "time": 0.00075
                }, 
                "collecting defs": {
                    "percent": 0.0, 
                    "time": 0.0
                }, 
                "variance inference": {
                    "percent": 0.0, 
                    "time": 0.0
                }, 
                "recursion limit": {
                    "percent": 0.0, 
                    "time": 0.0
                }, 
                "loop checking": {
                    "percent": 0.0, 
                    "time": 0.0
                }, 
                "item-types checking": {
                    "percent": 0.09099181073703368, 
                    "time": 0.001
                }, 
                "crate injection": {
                    "percent": 0.0, 
                    "time": 0.0
                }, 
                "expansion": {
                    "percent": 5.823475887170155, 
                    "time": 0.064
                }, 
                "region resolution": {
                    "percent": 0.18198362147406735, 
                    "time": 0.002
                }, 
                "early lint checks": {
                    "percent": 0.27297543221110104, 
                    "time": 0.003
                }, 
                "load_dep_graph": {
                    "percent": 0.0, 
                    "time": 0.0
                }, 
                "lowering ast -> hir": {
                    "percent": 0.45495905368516837, 
                    "time": 0.005
                }, 
                "maybe building test harness": {
                    "percent": 0.0, 
                    "time": 0.0
                }, 
                "AST validation": {
                    "percent": 0.0, 
                    "time": 0.0
                }, 
                "name resolution": {
                    "percent": 0.9099181073703367, 
                    "time": 0.01
                }, 
                "plugin loading": {
                    "percent": 0.0, 
                    "time": 0.0
                }, 
                "wf checking": {
                    "percent": 0.7279344858962694, 
                    "time": 0.008
                }, 
                "static item recursion checking": {
                    "percent": 0.0, 
                    "time": 0.0
                }, 
                "attribute checking": {
                    "percent": 0.0, 
                    "time": 0.0
                }, 
                "plugin registration": {
                    "percent": 0.0, 
                    "time": 0.0
                }, 
                "coherence checking": {
                    "percent": 0.9099181073703367, 
                    "time": 0.01
                }, 
                "indexing hir": {
                    "percent": 0.09099181073703368, 
                    "time": 0.001
                }, 
                "external crate/lib resolution": {
                    "percent": 9.099181073703368, 
                    "time": 0.1
                }
            }, 
            "total": 1.099, 
            "rss": {
                "looking for plugin registrar": 174, 
                "looking for entry point": 174, 
                "type collecting": 178, 
                "parsing": 46, 
                "item-bodies checking": 199, 
                "configuration": 46, 
                "assigning node ids": 88, 
                "language item collection": 174, 
                "complete gated feature checking": 88, 
                "checking for inline asm in case the target doesn't support it": 88, 
                "lifetime resolution": 174, 
                "collecting defs": 88, 
                "variance inference": 178, 
                "recursion limit": 46, 
                "loop checking": 175, 
                "item-types checking": 180, 
                "crate injection": 46, 
                "expansion": 88, 
                "region resolution": 175, 
                "early lint checks": 170, 
                "load_dep_graph": 175, 
                "lowering ast -> hir": 178, 
                "maybe building test harness": 88, 
                "AST validation": 170, 
                "name resolution": 174, 
                "plugin loading": 47, 
                "wf checking": 180, 
                "static item recursion checking": 175, 
                "attribute checking": 178, 
                "plugin registration": 47, 
                "coherence checking": 179, 
                "indexing hir": 178, 
                "external crate/lib resolution": 170
            }
        }
    ]
}